osekit/__init__.py
osekit/config.py
osekit/logging_config.yaml
osekit/logging_context.py
osekit/audio_backend/audio_backend.py
osekit/audio_backend/audio_file_manager.py
osekit/audio_backend/mseed_backend.py
osekit/audio_backend/soundfile_backend.py
osekit/core_api/__init__.py
osekit/core_api/audio_data.py
osekit/core_api/audio_dataset.py
osekit/core_api/audio_file.py
osekit/core_api/audio_item.py
osekit/core_api/base_data.py
osekit/core_api/base_dataset.py
osekit/core_api/base_file.py
osekit/core_api/base_item.py
osekit/core_api/event.py
osekit/core_api/frequency_scale.py
osekit/core_api/instrument.py
osekit/core_api/json_serializer.py
osekit/core_api/ltas_data.py
osekit/core_api/ltas_dataset.py
osekit/core_api/spectro_data.py
osekit/core_api/spectro_dataset.py
osekit/core_api/spectro_file.py
osekit/core_api/spectro_item.py
osekit/public_api/__init__.py
osekit/public_api/analysis.py
osekit/public_api/dataset.py
osekit/public_api/export_analysis.py
osekit/utils/__init__.py
osekit/utils/audio_utils.py
osekit/utils/core_utils.py
osekit/utils/formatting_utils.py
osekit/utils/job.py
osekit/utils/multiprocess_utils.py
osekit/utils/path_utils.py
osekit/utils/timestamp_utils.py
osekit-0.4.3.dist-info/METADATA
osekit-0.4.3.dist-info/WHEEL
osekit-0.4.3.dist-info/entry_points.txt
osekit-0.4.3.dist-info/licenses/LICENSE
osekit-0.4.3.dist-info/RECORD
