Metadata-Version: 2.4
Name: osekit
Version: 0.4.3
Summary: OSEkit
Author-email: OSmOSE team <osmose@ensta-bretagne.fr>
License-File: LICENSE
Classifier: Development Status :: 4 - Beta
Classifier: Programming Language :: Python :: 3.12
Classifier: Programming Language :: Python :: 3.13
Requires-Python: >=3.12
Requires-Dist: matplotlib>=3.10.7
Requires-Dist: notebook>=7.4.4
Requires-Dist: numpy>=2.2.6
Requires-Dist: pandas>=2.2.3
Requires-Dist: pytest>=8.3.5
Requires-Dist: pytz>=2025.2
Requires-Dist: pyyaml>=6.0.2
Requires-Dist: scipy>=1.15.3
Requires-Dist: soundfile>=0.13.1
Requires-Dist: soxr>=0.5.0.post1
Requires-Dist: tqdm>=4.67.1
Provides-Extra: mseed
Requires-Dist: obspy; extra == 'mseed'
